{"componentName":"com.moez.QKSMS.ui.messagelist.MessageListActivity","layoutFile":"activity_fragment","sensEntries":{"<com.moez.QKSMS.ui.messagelist.MessageListActivity: void onNewIntent(android.content.Intent)>":{"sensEntry":"<com.moez.QKSMS.ui.messagelist.MessageListActivity: void onNewIntent(android.content.Intent)>","sensTargets":["<java.net.ServerSocket: void <init>(int)>","<java.net.DatagramSocket: void <init>(int)>"],"views":{}},"<com.moez.QKSMS.ui.messagelist.MessageListActivity: void onActivityResult(int,int,android.content.Intent)>":{"sensEntry":"<com.moez.QKSMS.ui.messagelist.MessageListActivity: void onActivityResult(int,int,android.content.Intent)>","sensTargets":["<android.telephony.SmsManager: void sendMultipartTextMessage(java.lang.String,java.lang.String,java.util.ArrayList,java.util.ArrayList,java.util.ArrayList)>"],"views":{}},"<com.moez.QKSMS.ui.messagelist.MessageListActivity: void onCreate(android.os.Bundle)>":{"sensEntry":"<com.moez.QKSMS.ui.messagelist.MessageListActivity: void onCreate(android.os.Bundle)>","sensTargets":["<java.lang.reflect.Method: java.lang.Object invoke(java.lang.Object,java.lang.Object[])>"],"views":{}},"<com.moez.QKSMS.ui.messagelist.MessageListActivity: boolean onCreateOptionsMenu(android.view.Menu)>":{"sensEntry":"<com.moez.QKSMS.ui.messagelist.MessageListActivity: boolean onCreateOptionsMenu(android.view.Menu)>","sensTargets":["<java.net.ServerSocket: void <init>(int)>","<java.net.DatagramSocket: void <init>(int)>"],"views":{}}}}